Workbook

Sheet LÉEME
A1: CASHFLOW — Proyecto ILS/DME Turquía (DHMİ 2026/760533)
A3: Esta es una PLANTILLA. No contiene cifras económicas inventadas.
A5: • El MOTOR (calendario de cobros/pagos y porcentajes) sale 100% del contrato — hoja 'Datos contrato'.
A6: • Los IMPORTES en € los pones TÚ en la hoja 'Entradas' (celdas amarillas). Son datos de GECI.
A7: • La hoja 'Cashflow' calcula sola con fórmulas. Sin entradas, sale todo a 0 (es lo correcto).
A9: Qué es REAL (del contrato) y qué tienes que aportar TÚ:
A11: REAL (no se toca): cobros 40% embarque / 50% PAC / 10% FAC · sin anticipo · FAC = PAC + 12 meses ·
A12: entrega en máx. 3 embarques en máx. 840 días · duración 1.935 días ·
A13: garantía 2 años tras FAC · aval provisional 3% · aval cumplimiento 6%.
A15: LO PONES TÚ: valor de la oferta · valor de cada embarque · meses hasta PAC de cada lote ·
A16: coste de equipos (Indra) · coste de instalación · condiciones de pago a Indra ·
A17: coste anual de avales y de financiación (te los da tu banco).
... A20: Mientras no tengas esos números reales, el cashflow no puede dar un importe veraz.

Sheet Datos contrato
A1: DATOS REALES DEL CONTRATO (con referencia al documento)
A3: Concepto | B3: Valor | C3: Fuente
A4: Cliente | B4: DHMİ – State Airports Authority (Turquía) | C4: OBSERVACIONES / contrato
A5: Expediente (TRN) | B5: 2026/760533 | C5: Pliego
A6: Objeto | B6: 21 sistemas ILS/DME + 1 LLZ/DME | C6: Birim Fiyat / contrato Art.10
A7: Fecha límite de oferta | B7: 28/07/2026 11:00 | C7: OBSERVACIONES
A8: Validez de la oferta | B8: 180 días | C8: OBSERVACIONES / pliego
A9: Moneda admitida | B9: TRY / USD / EUR | C9: Contrato Art.12.2.1
A10: Duración del contrato | B10: 1.935 días naturales | C10: Contrato Art.9.1
A11: Plazo de entrega | B11: máx. 3 embarques en máx. 840 días | C11: Contrato Art.10.3.1
A12: Incoterm (contratista extranjero) | B12: DPU (Delivered at Place Unloaded) | C12: Contrato Art.10.3
A13: Cobro 1 | B13: 40% contra embarque (docs/inspección) | C13: Contrato Art.12.2.3
A14: Cobro 2 | B14: 50% tras formación + PAC | C14: Contrato Art.12.2.3
... A28: Estado de la oferta económica | B28: NO existe modelo de Turquía (solo plantillas de otros países) | C28: Carpeta 01_Economical_Proposals
A30: CANTIDADES (Birim Fiyat Teklif Cetveli) — sin precios (la lista oficial va en blanco)
A31: Concepto | B31: Cantidad
A32: Localizer (equipo+antena) | B32: 22
A33: Glide-Path (equipo+antena) | B33: 21
A34: DME (equipo+antena) | B34: 22
A35: Unidad control/estado remoto | B35: 22
A36: Control remoto (PC) | B36: 65
A37: Mantenimiento remoto (portátil) | B37: 22
A38: Shelter LLZ y GP | B38: 43
A39: Set repuestos ILS (full)+carga | B39: 21
A40: Set repuestos Localizer (full)+carga | B40: 1
A41: Set repuestos DME | B41: 22

Sheet Entradas
A1: ENTRADAS — rellena las celdas amarillas con datos REALES de GECI
A3: Valor de la oferta / contrato (sin IVA)
A4: Pago a Indra al PEDIDO (%)
A5: Pago a Indra al EMBARQUE (%)
A6: Meses de antelación del pedido antes del embarque
A7: Coste anual del aval (te lo da tu banco) (%)
A8: Coste anual de financiación del circulante (%)
A10: Por cada LOTE de embarque (máx. 3, dentro de 840 días). Deja en blanco los que no uses:
A11: Lote | B11: Mes de embarque (desde firma, ≤28) | C11: Valor del embarque (€) | D11: Meses hasta PAC (tu plan de instalación) | E11: Coste equipos del lote (Indra) (€) | F11: Coste instalación del lote (€)
A12: Lote 1
A13: Lote 2
A14: Lote 3
A16: Comprobación: la suma de 'Valor del embarque' debería igualar el valor de la oferta.
A17: Suma valores de embarque: | B17: =SUM(C12:C14) | C17: =IF(B17=B3,"OK","≠ revisar")

Sheet Cashflow
A1: CASHFLOW MENSUAL (se calcula solo desde 'Entradas')
A3: Mes (desde firma) | B3: Cobro 40% embarque | C3: Cobro 50% PAC | D3: Cobro 10% FAC | E3: INGRESOS | F3: Pago pedido Indra | G3: Pago embarque Indra | H3: Instalación | I3: Coste aval | J3: Coste financiero | K3: COSTES | L3: NETO mes | M3: CAJA acumulada
A4: 0 | B4: =SUMPRODUCT((Entradas!$B$12:$B$14=$A4)*Entradas!$C$12:$C$14)*0.4 | C4: =SUMPRODUCT(((Entradas!$B$12:$B$14+Entradas!$D$12:$D$14)=$A4)*Entradas!$C$12:$C$14)*0.5 | D4: =SUMPRODUCT(((Entradas!$B$12:$B$14+Entradas!$D$12:$D$14+12)=$A4)*Entradas!$C$12:$C$14)*0.1 | E4: =SUM(B4:D4) | F4: =SUMPRODUCT(((Entradas!$B$12:$B$14-Entradas!$B$6)=$A4)*Entradas!$E$12:$E$14)*Entradas!$B$4 | G4: =SUMPRODUCT((Entradas!$B$12:$B$14=$A4)*Entradas!$E$12:$E$14)*Entradas!$B$5 | H4: =SUMPRODUCT((Entradas!$B$12:$B$14<=$A4)*((Entradas!$B$12:$B$14+Entradas!$D$12:$D$14)>$A4)*(Entradas!$F$12:$F$14/(Entradas!$D$12:$D$14+(Entradas!$D$12:$D$14=0)))) | I4: =Entradas!$B$3*0.06*Entradas!$B$7/12 | J4: 0 | K4: =SUM(F4:J4) | L4: =E4-K4 | M4: =L4
A5: 1 | B5: =SUMPRODUCT((Entradas!$B$12:$B$14=$A5)*Entradas!$C$12:$C$14)*0.4 | C5: =SUMPRODUCT(((Entradas!$B$12:$B$14+Entradas!$D$12:$D$14)=$A5)*Entradas!$C$12:$C$14)*0.5 | D5: =SUMPRODUCT(((Entradas!$B$12:$B$14+Entradas!$D$12:$D$14+12)=$A5)*Entradas!$C$12:$C$14)*0.1 | E5: =SUM(B5:D5) | F5: =SUMPRODUCT(((Entradas!$B$12:$B$14-Entradas!$B$6)=$A5)*Entradas!$E$12:$E$14)*Entradas!$B$4 | G5: =SUMPRODUCT((Entradas!$B$12:$B$14=$A5)*Entradas!$E$12:$E$14)*Entradas!$B$5 | H5: =SUMPRODUCT((Entradas!$B$12:$B$14<=$A5)*((Entradas!$B$12:$B$14+Entradas!$D$12:$D$14)>$A5)*(Entradas!$F$12:$F$14/(Entradas!$D$12:$D$14+(Entradas!$D$12:$D$14=0)))) | I5: =Entradas!$B$3*0.06*Entradas!$B$7/12 | J5: =IF(M4<0,-M4*Entradas!$B$8/12,0) | K5: =SUM(F5:J5) | L5: =E5-K5 | M5: =M4+L5
A6: 2 | B6: =SUMPRODUCT((Entradas!$B$12:$B$14=$A6)*Entradas!$C$12:$C$14)*0.4 | C6: =SUMPRODUCT(((Entradas!$B$12:$B$14+Entradas!$D$12:$D$14)=$A6)*Entradas!$C$12:$C$14)*0.5 | D6: =SUMPRODUCT(((Entradas!$B$12:$B$14+Entradas!$D$12:$D$14+12)=$A6)*Entradas!$C$12:$C$14)*0.1 | E6: =SUM(B6:D6) | F6: =SUMPRODUCT(((Entradas!$B$12:$B$14-Entradas!$B$6)=$A6)*Entradas!$E$12:$E$14)*Entradas!$B$4 | G6: =SUMPRODUCT((Entradas!$B$12:$B$14=$A6)*Entradas!$E$12:$E$14)*Entradas!$B$5 | H6: =SUMPRODUCT((Entradas!$B$12:$B$14<=$A6)*((Entradas!$B$12:$B$14+Entradas!$D$12:$D$14)>$A6)*(Entradas!$F$12:$F$14/(Entradas!$D$12:$D$14+(Entradas!$D$12:$D$14=0)))) | I6: =Entradas!$B$3*0.06*Entradas!$B$7/12 | J6: =IF(M5<0,-M5*Entradas!$B$8/12,0) | K6: =SUM(F6:J6) | L6: =E6-K6 | M6: =M5+L6
A7: 3 | B7: =SUMPRODUCT((Entradas!$B$12:$B$14=$A7)*Entradas!$C$12:$C$14)*0.4 | C7: =SUMPRODUCT(((Entradas!$B$12:$B$14+Entradas!$D$12:$D$14)=$A7)*Entradas!$C$12:$C$14)*0.5 | D7: =SUMPRODUCT(((Entradas!$B$12:$B$14+Entradas!$D$12:$D$14+12)=$A7)*Entradas!$C$12:$C$14)*0.1 | E7: =SUM(B7:D7) | F7: =SUMPRODUCT(((Entradas!$B$12:$B$14-Entradas!$B$6)=$A7)*Entradas!$E$12:$E$14)*Entradas!$B$4 | G7: =SUMPRODUCT((Entradas!$B$12:$B$14=$A7)*Entradas!$E$12:$E$14)*Entradas!$B$5 | H7: =SUMPRODUCT((Entradas!$B$12:$B$14<=$A7)*((Entradas!$B$12:$B$14+Entradas!$D$12:$D$14)>$A7)*(Entradas!$F$12:$F$14/(Entradas!$D$12:$D$14+(Entradas!$D$12:$D$14=0)))) | I7: =Entradas!$B$3*0.06*Entradas!$B$7/12 | J7: =IF(M6<0,-M6*Entradas!$B$8/12,0) | K7: =SUM(F7:J7) | L7: =E7-K7 | M7: =M6+L7
A8: 4 | B8: =SUMPRODUCT((Entradas!$B$12:$B$14=$A8)*Entradas!$C$12:$C$14)*0.4 | C8: =SUMPRODUCT(((Entradas!$B$12:$B$14+Entradas!$D$12:$D$14)=$A8)*Entradas!$C$12:$C$14)*0.5 | D8: =SUMPRODUCT(((Entradas!$B$12:$B$14+Entradas!$D$12:$D$14+12)=$A8)*Entradas!$C$12:$C$14)*0.1 | E8: =SUM(B8:D8) | F8: =SUMPRODUCT(((Entradas!$B$12:$B$14-Entradas!$B$6)=$A8)*Entradas!$E$12:$E$14)*Entradas!$B$4 | G8: =SUMPRODUCT((Entradas!$B$12:$B$14=$A8)*Entradas!$E$12:$E$14)*Entradas!$B$5 | H8: =SUMPRODUCT((Entradas!$B$12:$B$14<=$A8)*((Entradas!$B$12:$B$14+Entradas!$D$12:$D$14)>$A8)*(Entradas!$F$12:$F$14/(Entradas!$D$12:$D$14+(Entradas!$D$12:$D$14=0)))) | I8: =Entradas!$B$3*0.06*Entradas!$B$7/12 | J8: =IF(M7<0,-M7*Entradas!$B$8/12,0) | K8: =SUM(F8:J8) | L8: =E8-K8 | M8: =M7+L8
A9: 5 | B9: =SUMPRODUCT((Entradas!$B$12:$B$14=$A9)*Entradas!$C$12:$C$14)*0.4 | C9: =SUMPRODUCT(((Entradas!$B$12:$B$14+Entradas!$D$12:$D$14)=$A9)*Entradas!$C$12:$C$14)*0.5 | D9: =SUMPRODUCT(((Entradas!$B$12:$B$14+Entradas!$D$12:$D$14+12)=$A9)*Entradas!$C$12:$C$14)*0.1 | E9: =SUM(B9:D9) | F9: =SUMPRODUCT(((Entradas!$B$12:$B$14-Entradas!$B$6)=$A9)*Entradas!$E$12:$E$14)*Entradas!$B$4 | G9: =SUMPRODUCT((Entradas!$B$12:$B$14=$A9)*Entradas!$E$12:$E$14)*Entradas!$B$5 | H9: =SUMPRODUCT((Entradas!$B$12:$B$14<=$A9)*((Entradas!$B$12:$B$14+Entradas!$D$12:$D$14)>$A9)*(Entradas!$F$12:$F$14/(Entradas!$D$12:$D$14+(Entradas!$D$12:$D$14=0)))) | I9: =Entradas!$B$3*0.06*Entradas!$B$7/12 | J9: =IF(M8<0,-M8*Entradas!$B$8/12,0) | K9: =SUM(F9:J9) | L9: =E9-K9 | M9: =M8+L9
A10: 6 | B10: =SUMPRODUCT((Entradas!$B$12:$B$14=$A10)*Entradas!$C$12:$C$14)*0.4 | C10: =SUMPRODUCT(((Entradas!$B$12:$B$14+Entradas!$D$12:$D$14)=$A10)*Entradas!$C$12:$C$14)*0.5 | D10: =SUMPRODUCT(((Entradas!$B$12:$B$14+Entradas!$D$12:$D$14+12)=$A10)*Entradas!$C$12:$C$14)*0.1 | E10: =SUM(B10:D10) | F10: =SUMPRODUCT(((Entradas!$B$12:$B$14-Entradas!$B$6)=$A10)*Entradas!$E$12:$E$14)*Entradas!$B$4 | G10: =SUMPRODUCT((Entradas!$B$12:$B$14=$A10)*Entradas!$E$12:$E$14)*Entradas!$B$5 | H10: =SUMPRODUCT((Entradas!$B$12:$B$14<=$A10)*((Entradas!$B$12:$B$14+Entradas!$D$12:$D$14)>$A10)*(Entradas!$F$12:$F$14/(Entradas!$D$12:$D$14+(Entradas!$D$12:$D$14=0)))) | I10: =Entradas!$B$3*0.06*Entradas!$B$7/12 | J10: =IF(M9<0,-M9*Entradas!$B$8/12,0) | K10: =SUM(F10:J10) | L10: =E10-K10 | M10: =M9+L10
A11: 7 | B11: =SUMPRODUCT((Entradas!$B$12:$B$14=$A11)*Entradas!$C$12:$C$14)*0.4 | C11: =SUMPRODUCT(((Entradas!$B$12:$B$14+Entradas!$D$12:$D$14)=$A11)*Entradas!$C$12:$C$14)*0.5 | D11: =SUMPRODUCT(((Entradas!$B$12:$B$14+Entradas!$D$12:$D$14+12)=$A11)*Entradas!$C$12:$C$14)*0.1 | E11: =SUM(B11:D11) | F11: =SUMPRODUCT(((Entradas!$B$12:$B$14-Entradas!$B$6)=$A11)*Entradas!$E$12:$E$14)*Entradas!$B$4 | G11: =SUMPRODUCT((Entradas!$B$12:$B$14=$A11)*Entradas!$E$12:$E$14)*Entradas!$B$5 | H11: =SUMPRODUCT((Entradas!$B$12:$B$14<=$A11)*((Entradas!$B$12:$B$14+Entradas!$D$12:$D$14)>$A11)*(Entradas!$F$12:$F$14/(Entradas!$D$12:$D$14+(Entradas!$D$12:$D$14=0)))) | I11: =Entradas!$B$3*0.06*Entradas!$B$7/12 | J11: =IF(M10<0,-M10*Entradas!$B$8/12,0) | K11: =SUM(F11:J11) | L11: =E11-K11 | M11: =M10+L11
A12: 8 | B12: =SUMPRODUCT((Entradas!$B$12:$B$14=$A12)*Entradas!$C$12:$C$14)*0.4 | C12: =SUMPRODUCT(((Entradas!$B$12:$B$14+Entradas!$D$12:$D$14)=$A12)*Entradas!$C$12:$C$14)*0.5 | D12: =SUMPRODUCT(((Entradas!$B$12:$B$14+Entradas!$D$12:$D$14+12)=$A12)*Entradas!$C$12:$C$14)*0.1 | E12: =SUM(B12:D12) | F12: =SUMPRODUCT(((Entradas!$B$12:$B$14-Entradas!$B$6)=$A12)*Entradas!$E$12:$E$14)*Entradas!$B$4 | G12: =SUMPRODUCT((Entradas!$B$12:$B$14=$A12)*Entradas!$E$12:$E$14)*Entradas!$B$5 | H12: =SUMPRODUCT((Entradas!$B$12:$B$14<=$A12)*((Entradas!$B$12:$B$14+Entradas!$D$12:$D$14)>$A12)*(Entradas!$F$12:$F$14/(Entradas!$D$12:$D$14+(Entradas!$D$12:$D$14=0)))) | I12: =Entradas!$B$3*0.06*Entradas!$B$7/12 | J12: =IF(M11<0,-M11*Entradas!$B$8/12,0) | K12: =SUM(F12:J12) | L12: =E12-K12 | M12: =M11+L12
A13: 9 | B13: =SUMPRODUCT((Entradas!$B$12:$B$14=$A13)*Entradas!$C$12:$C$14)*0.4 | C13: =SUMPRODUCT(((Entradas!$B$12:$B$14+Entradas!$D$12:$D$14)=$A13)*Entradas!$C$12:$C$14)*0.5 | D13: =SUMPRODUCT(((Entradas!$B$12:$B$14+Entradas!$D$12:$D$14+12)=$A13)*Entradas!$C$12:$C$14)*0.1 | E13: =SUM(B13:D13) | F13: =SUMPRODUCT(((Entradas!$B$12:$B$14-Entradas!$B$6)=$A13)*Entradas!$E$12:$E$14)*Entradas!$B$4 | G13: =SUMPRODUCT((Entradas!$B$12:$B$14=$A13)*Entradas!$E$12:$E$14)*Entradas!$B$5 | H13: =SUMPRODUCT((Entradas!$B$12:$B$14<=$A13)*((Entradas!$B$12:$B$14+Entradas!$D$12:$D$14)>$A13)*(Entradas!$F$12:$F$14/(Entradas!$D$12:$D$14+(Entradas!$D$12:$D$14=0)))) | I13: =Entradas!$B$3*0.06*Entradas!$B$7/12 | J13: =IF(M12<0,-M12*Entradas!$B$8/12,0) | K13: =SUM(F13:J13) | L13: =E13-K13 | M13: =M12+L13
A14: 10 | B14: =SUMPRODUCT((Entradas!$B$12:$B$14=$A14)*Entradas!$C$12:$C$14)*0.4 | C14: =SUMPRODUCT(((Entradas!$B$12:$B$14+Entradas!$D$12:$D$14)=$A14)*Entradas!$C$12:$C$14)*0.5 | D14: =SUMPRODUCT(((Entradas!$B$12:$B$14+Entradas!$D$12:$D$14+12)=$A14)*Entradas!$C$12:$C$14)*0.1 | E14: =SUM(B14:D14) | F14: =SUMPRODUCT(((Entradas!$B$12:$B$14-Entradas!$B$6)=$A14)*Entradas!$E$12:$E$14)*Entradas!$B$4 | G14: =SUMPRODUCT((Entradas!$B$12:$B$14=$A14)*Entradas!$E$12:$E$14)*Entradas!$B$5 | H14: =SUMPRODUCT((Entradas!$B$12:$B$14<=$A14)*((Entradas!$B$12:$B$14+Entradas!$D$12:$D$14)>$A14)*(Entradas!$F$12:$F$14/(Entradas!$D$12:$D$14+(Entradas!$D$12:$D$14=0)))) | I14: =Entradas!$B$3*0.06*Entradas!$B$7/12 | J14: =IF(M13<0,-M13*Entradas!$B$8/12,0) | K14: =SUM(F14:J14) | L14: =E14-K14 | M14: =M13+L14
A15: 11 | B15: =SUMPRODUCT((Entradas!$B$12:$B$14=$A15)*Entradas!$C$12:$C$14)*0.4 | C15: =SUMPRODUCT(((Entradas!$B$12:$B$14+Entradas!$D$12:$D$14)=$A15)*Entradas!$C$12:$C$14)*0.5 | D15: =SUMPRODUCT(((Entradas!$B$12:$B$14+Entradas!$D$12:$D$14+12)=$A15)*Entradas!$C$12:$C$14)*0.1 | E15: =SUM(B15:D15) | F15: =SUMPRODUCT(((Entradas!$B$12:$B$14-Entradas!$B$6)=$A15)*Entradas!$E$12:$E$14)*Entradas!$B$4 | G15: =SUMPRODUCT((Entradas!$B$12:$B$14=$A15)*Entradas!$E$12:$E$14)*Entradas!$B$5 | H15: =SUMPRODUCT((Entradas!$B$12:$B$14<=$A15)*((Entradas!$B$12:$B$14+Entradas!$D$12:$D$14)>$A15)*(Entradas!$F$12:$F$14/(Entradas!$D$12:$D$14+(Entradas!$D$12:$D$14=0)))) | I15: =Entradas!$B$3*0.06*Entradas!$B$7/12 | J15: =IF(M14<0,-M14*Entradas!$B$8/12,0) | K15: =SUM(F15:J15) | L15: =E15-K15 | M15: =M14+L15
A16: 12 | B16: =SUMPRODUCT((Entradas!$B$12:$B$14=$A16)*Entradas!$C$12:$C$14)*0.4 | C16: =SUMPRODUCT(((Entradas!$B$12:$B$14+Entradas!$D$12:$D$14)=$A16)*Entradas!$C$12:$C$14)*0.5 | D16: =SUMPRODUCT(((Entradas!$B$12:$B$14+Entradas!$D$12:$D$14+12)=$A16)*Entradas!$C$12:$C$14)*0.1 | E16: =SUM(B16:D16) | F16: =SUMPRODUCT(((Entradas!$B$12:$B$14-Entradas!$B$6)=$A16)*Entradas!$E$12:$E$14)*Entradas!$B$4 | G16: =SUMPRODUCT((Entradas!$B$12:$B$14=$A16)*Entradas!$E$12:$E$14)*Entradas!$B$5 | H16: =SUMPRODUCT((Entradas!$B$12:$B$14<=$A16)*((Entradas!$B$12:$B$14+Entradas!$D$12:$D$14)>$A16)*(Entradas!$F$12:$F$14/(Entradas!$D$12:$D$14+(Entradas!$D$12:$D$14=0)))) | I16: =Entradas!$B$3*0.06*Entradas!$B$7/12 | J16: =IF(M15<0,-M15*Entradas!$B$8/12,0) | K16: =SUM(F16:J16) | L16: =E16-K16 | M16: =M15+L16
... A76: 72 | B76: =SUMPRODUCT((Entradas!$B$12:$B$14=$A76)*Entradas!$C$12:$C$14)*0.4 | C76: =SUMPRODUCT(((Entradas!$B$12:$B$14+Entradas!$D$12:$D$14)=$A76)*Entradas!$C$12:$C$14)*0.5 | D76: =SUMPRODUCT(((Entradas!$B$12:$B$14+Entradas!$D$12:$D$14+12)=$A76)*Entradas!$C$12:$C$14)*0.1 | E76: =SUM(B76:D76) | F76: =SUMPRODUCT(((Entradas!$B$12:$B$14-Entradas!$B$6)=$A76)*Entradas!$E$12:$E$14)*Entradas!$B$4 | G76: =SUMPRODUCT((Entradas!$B$12:$B$14=$A76)*Entradas!$E$12:$E$14)*Entradas!$B$5 | H76: =SUMPRODUCT((Entradas!$B$12:$B$14<=$A76)*((Entradas!$B$12:$B$14+Entradas!$D$12:$D$14)>$A76)*(Entradas!$F$12:$F$14/(Entradas!$D$12:$D$14+(Entradas!$D$12:$D$14=0)))) | I76: =Entradas!$B$3*0.06*Entradas!$B$7/12 | J76: =IF(M75<0,-M75*Entradas!$B$8/12,0) | K76: =SUM(F76:J76) | L76: =E76-K76 | M76: =M75+L76
A78: TOTALES / KPIs
A79: Ingresos totales | B79: =SUM(E4:E76)
A80: Costes totales | B80: =SUM(K4:K76)
A81: Margen (beneficio) | B81: =B79-B80
A82: PICO de financiación (caja mín.) | B82: =MIN(M4:M76)
A83: Caja final | B83: =M76

Sheet Lo Raro
A1: LO RARO / BANDERAS ROJAS (solo hechos documentados)
A3: # | B3: Hallazgo (documentado) | C3: Por qué importa | D3: Fuente
A4: 1 | B4: Sin anticipo + cobro 40/50/10 muy diferido | C4: Pagas a tu proveedor antes de cobrar; el contrato exige financiar el circulante durante años. | D4: Contrato Art.13.1 y 12.2.3
A5: 2 | B5: Precio fijo sin revisión durante ~5,3 años | C5: Subidas de coste/divisa no recuperables; crítico si la oferta es en liras turcas. | D5: Contrato Art.14 / Pliego Art.43
A6: 3 | B6: No existe oferta económica de Turquía | C6: Imposible cifrar el cashflow con datos reales; solo hay plantillas de otros países. | D6: Carpeta 01_Economical_Proposals
A7: 4 | B7: Avales 3% + 6% retenidos mucho tiempo | C7: El de cumplimiento se libera ½ tras PAC y ½ tras 2 años de garantía: línea ocupada años. | D7: Pliego Art.37 / Contrato Art.11.3
A8: 5 | B8: Proveedor único (Indra) con certificaciones obligatorias | C8: Sin Authorised Dealer + Manufacturer's Certificate + CAT III Flight Check NO se puede licitar. | D8: RESUMEN INDRA / OBSERVACIONES
A9: 6 | B9: Subcontratación prohibida; consorcios no admitidos | C9: El modelo comprar-e-instalar debe estructurarse como suministro o UTE. | D9: Contrato Art.15 / Pliego
A10: 7 | B10: DPU + aduanas/importación a cargo del contratista | C10: Más capital circulante: transporte, despacho, almacenaje y permisos los adelanta GECI. | D10: Contrato Art.10.3
A11: 8 | B11: Factibilidad interna 53% 'APTO' (borderline) | C11: La propia hoja marca financiación/adquisiciones como riesgo. | D11: F-POI-16/15
A12: 9 | B12: Aproximaciones de valor incoherentes | C12: Experiencia 20%≈5M€ implica ~25M€, pero avales 3%≈600k/6%≈1,2M implican ~20M€. Falta fijar el valor. | D12: OBSERVACIONES
